.coveragerc
.flake8
.gitignore
.gitlab-ci.yml
.readthedocs.yml
CODE_OF_CONDUCT.md
LICENSE
Makefile
README.rst
requirements.txt
setup.cfg
setup.py
test-requirements.txt
tox.ini
docs/api.rst
docs/conf.py
docs/examples.rst
docs/index.rst
docs/_static/favicon.ico
examples/circuitroomba_interface.py
examples/circuitroomba_roomba.py
examples/roomba_oi_no_helper.py
specs/circuit_playground_Adafruit_Circuit_Playground_Express_Pinout.png
specs/iRobot_Roomba_600_Open_Interface_Spec.pdf
src/__init__.py
src/circuitroomba/__init__.py
src/circuitroomba.egg-info/PKG-INFO
src/circuitroomba.egg-info/SOURCES.txt
src/circuitroomba.egg-info/dependency_links.txt
src/circuitroomba.egg-info/requires.txt
src/circuitroomba.egg-info/top_level.txt
src/circuitroomba/series6/__init__.py
src/circuitroomba/series6/interface.py
src/circuitroomba/series6/opcode.py
src/circuitroomba/series6/roomba.py
tests/__init__.py
tests/integration/__init__.py
tests/integration/series6/__init__.py
tests/unit/__init__.py
tests/unit/series6/__init__.py
tests/unit/series6/test_interface.py
tests/unit/series6/test_opcode.py
tests/unit/series6/test_roomba.py