Metadata-Version: 2.1
Name: circuitroomba
Version: 0.1.0
Summary: CircuitPython helper library for interfacing with Roomba     Open Interface devices.
Home-page: https://gitlab.com/AlexanderHagerman/circuitroomba
Author: Alexander Hagerman
Author-email: alexander@unexpectedeof.net
License: MIT
Keywords: adafruit blinka circuitpython micropythoncircuitroomba circuitroomba robot automation roomba interface
Platform: UNKNOWN
Classifier: Development Status :: 3 - Alpha
Classifier: Intended Audience :: Developers
Classifier: Topic :: Software Development :: Libraries
Classifier: Topic :: System :: Hardware
Classifier: License :: OSI Approved :: MIT License
Classifier: Programming Language :: Python :: 3
Classifier: Programming Language :: Python :: 3.7
